env_check/cli.py
env_check/core.py
env_check_utils-0.1.4.dist-info/METADATA
env_check_utils-0.1.4.dist-info/WHEEL
env_check_utils-0.1.4.dist-info/entry_points.txt
env_check_utils-0.1.4.dist-info/top_level.txt
env_check_utils-0.1.4.dist-info/RECORD
