Metadata-Version: 2.4
Name: env-check-utils
Version: 0.1.4
Summary: A CLI tool to check, validate, and manage .env files
Author-email: Rohit Thakan <rohitthakan2001@gmail.com>
Requires-Python: >=3.8
Requires-Dist: PyYAML>=6.0
Requires-Dist: toml>=0.10; python_version < "3.11"
